gmap_scraper/__init__.py
gmap_scraper/scrape.py
gmap_scraper-0.1.0.dist-info/licenses/LICENSE
gmap_scraper-0.1.0.dist-info/METADATA
gmap_scraper-0.1.0.dist-info/WHEEL
gmap_scraper-0.1.0.dist-info/entry_points.txt
gmap_scraper-0.1.0.dist-info/top_level.txt
gmap_scraper-0.1.0.dist-info/RECORD
